[
	{
		"title": "Overview",
		"link": "/docs/overview"
	},
	{
		"title": "CLI",
		"link": "/docs/cli"
	},
	{
		"title": "Configuration",
		"link": "/docs/configuration"
	},
	{
		"title": "Deployment",
		"showDropdown": false,
		"children": [
			{
				"title": "Overview",
				"link": "/docs/deploy/overview"
			},
			{
				"title": "Docker",
				"link": "/docs/deploy/docker"
			},
			{
				"title": "Hobby",
				"link": "/docs/deploy/hobby"
			},
			{
				"title": "DigitalOcean",
				"link": "/docs/deploy/digitalocean"
			}
		]
	},
	{
		"title": "Product Manual",
		"showDropdown": false,
		"children": [
			{
				"title": "Overview",
				"link": "/docs/manual/overview"
			},
			{
				"title": "Organizations and Projects",
				"link": "/docs/manual/organizations-and-projects"
			},
			{
				"title": "Sources",
				"link": "/docs/manual/sources"
			},
			{
				"title": "Subscriptions",
				"link": "/docs/manual/subscriptions"
			},
			{
				"title": "Event and Event Deliveries",
				"link": "/docs/manual/events-and-event-deliveries"
			},
			{
				"title": "Applications and Endpoints",
				"link": "/docs/manual/applications-and-endpoints"
			}
		]
	},
	{
		"title": "App Portal",
		"link": "/docs/app-portal"
	},
	{
		"title": "SDK",
		"link": "/docs/sdk"
	},
	{
		"title": "Release Notes",
		"showDropdown": false,
		"children": [
			{
				"title": "Overview",
				"link": "/docs/releases/overview"
			},
			{
				"title": "v0.5",
				"link": "/docs/releases/version-5"
			},
			{
				"title": "v0.6",
				"link": "/docs/releases/version-6"
			}
		]
	},
	{
		"title": "Glossary",
		"link": "/docs/glossary"
	}
]
